Polygon/IO.py
Polygon/Shapes.py
Polygon/Utils.py
Polygon/__init__.py
Polygon/cPolygon.cp38-win_amd64.pyd
Polygon3-3.0.8.dist-info/METADATA
Polygon3-3.0.8.dist-info/WHEEL
Polygon3-3.0.8.dist-info/top_level.txt
Polygon3-3.0.8.dist-info/RECORD
