Metadata-Version: 2.1
Name: Polygon3
Version: 3.0.8
Summary: Polygon3 is a Python-3 package that handles polygonal shapes in 2D
Home-page: http://www.j-raedler.de/projects/polygon
Author: Joerg Raedler
Author-email: joerg@j-raedler.de
Maintainer: Joerg Raedler
Maintainer-email: joerg@j-raedler.de
License: LGPL for Polygon, other for gpc
Platform: UNKNOWN
Classifier: Development Status :: 5 - Production/Stable
Classifier: Intended Audience :: Developers
Classifier: Intended Audience :: Science/Research
Classifier: License :: OSI Approved :: GNU Library or Lesser General Public License (LGPL)
Classifier: License :: Other/Proprietary License
Classifier: Programming Language :: C
Classifier: Programming Language :: Python :: 3
Classifier: Programming Language :: Python :: 3.0
Classifier: Programming Language :: Python :: 3.1
Classifier: Programming Language :: Python :: 3.2
Classifier: Programming Language :: Python :: 3.3
Classifier: Operating System :: POSIX :: Linux
Classifier: Operating System :: Microsoft :: Windows
Classifier: Operating System :: MacOS :: MacOS X
Classifier: Topic :: Scientific/Engineering :: Mathematics
Classifier: Topic :: Scientific/Engineering :: Visualization
